[
    {
        "?v0": "http://db.uwaterloo.ca/~galuc/wsdbm/Product19274",
        "?v9": "\"5368\"^^<http://www.w3.org/2001/XMLSchema#integer>",
        "?v11": "\"don touch refracting procession ulcers Albuquerque infinitives frigidly\"",
        "?v10": "\"Sioux's\"",
        "?v4": "http://db.uwaterloo.ca/~galuc/wsdbm/Review49099",
        "?v8": "\"space's confusion catchwords air knowledge sexagenarian formaldehyde's aesthetics's columned\"",
        "?v7": "\"salesman's escrows specifying underhandedly bin novel's mumbling vaccine's meteors typewrote nationalism's puck's Mexicans\"",
        "?v5": "\"8\"^^<http://www.w3.org/2001/XMLSchema#integer>",
        "?v1": "http://db.uwaterloo.ca/~galuc/wsdbm/Topic161",
        "?v2": "http://db.uwaterloo.ca/~galuc/wsdbm/Product10029",
        "?v12": "http://db.uwaterloo.ca/~galuc/wsdbm/Purchase74846",
        "?v6": "http://db.uwaterloo.ca/~galuc/wsdbm/User49784"
    },
    {
        "?v0": "http://db.uwaterloo.ca/~galuc/wsdbm/Product19274",
        "?v9": "\"5368\"^^<http://www.w3.org/2001/XMLSchema#integer>",
        "?v11": "\"don touch refracting procession ulcers Albuquerque infinitives frigidly\"",
        "?v10": "\"Sioux's\"",
        "?v4": "http://db.uwaterloo.ca/~galuc/wsdbm/Review49099",
        "?v8": "\"space's confusion catchwords air knowledge sexagenarian formaldehyde's aesthetics's columned\"",
        "?v7": "\"salesman's escrows specifying underhandedly bin novel's mumbling vaccine's meteors typewrote nationalism's puck's Mexicans\"",
        "?v5": "\"8\"^^<http://www.w3.org/2001/XMLSchema#integer>",
        "?v1": "http://db.uwaterloo.ca/~galuc/wsdbm/Topic161",
        "?v2": "http://db.uwaterloo.ca/~galuc/wsdbm/Product10110",
        "?v12": "http://db.uwaterloo.ca/~galuc/wsdbm/Purchase74846",
        "?v6": "http://db.uwaterloo.ca/~galuc/wsdbm/User49784"
    },
    {
        "?v0": "http://db.uwaterloo.ca/~galuc/wsdbm/Product19274",
        "?v9": "\"5368\"^^<http://www.w3.org/2001/XMLSchema#integer>",
        "?v11": "\"don touch refracting procession ulcers Albuquerque infinitives frigidly\"",
        "?v10": "\"Sioux's\"",
        "?v4": "http://db.uwaterloo.ca/~galuc/wsdbm/Review49099",
        "?v8": "\"space's confusion catchwords air knowledge sexagenarian formaldehyde's aesthetics's columned\"",
        "?v7": "\"salesman's escrows specifying underhandedly bin novel's mumbling vaccine's meteors typewrote nationalism's puck's Mexicans\"",
        "?v5": "\"8\"^^<http://www.w3.org/2001/XMLSchema#integer>",
        "?v1": "http://db.uwaterloo.ca/~galuc/wsdbm/Topic161",
        "?v2": "http://db.uwaterloo.ca/~galuc/wsdbm/Product10222",
        "?v12": "http://db.uwaterloo.ca/~galuc/wsdbm/Purchase74846",
        "?v6": "http://db.uwaterloo.ca/~galuc/wsdbm/User49784"
    },
    {
        "?v0": "http://db.uwaterloo.ca/~galuc/wsdbm/Product19274",
        "?v9": "\"5368\"^^<http://www.w3.org/2001/XMLSchema#integer>",
        "?v11": "\"don touch refracting procession ulcers Albuquerque infinitives frigidly\"",
        "?v10": "\"Sioux's\"",
        "?v4": "http://db.uwaterloo.ca/~galuc/wsdbm/Review49099",
        "?v8": "\"space's confusion catchwords air knowledge sexagenarian formaldehyde's aesthetics's columned\"",
        "?v7": "\"salesman's escrows specifying underhandedly bin novel's mumbling vaccine's meteors typewrote nationalism's puck's Mexicans\"",
        "?v5": "\"8\"^^<http://www.w3.org/2001/XMLSchema#integer>",
        "?v1": "http://db.uwaterloo.ca/~galuc/wsdbm/Topic161",
        "?v2": "http://db.uwaterloo.ca/~galuc/wsdbm/Product10265",
        "?v12": "http://db.uwaterloo.ca/~galuc/wsdbm/Purchase74846",
        "?v6": "http://db.uwaterloo.ca/~galuc/wsdbm/User49784"
    },
    {
        "?v0": "http://db.uwaterloo.ca/~galuc/wsdbm/Product19274",
        "?v9": "\"5368\"^^<http://www.w3.org/2001/XMLSchema#integer>",
        "?v11": "\"don touch refracting procession ulcers Albuquerque infinitives frigidly\"",
        "?v10": "\"Sioux's\"",
        "?v4": "http://db.uwaterloo.ca/~galuc/wsdbm/Review49099",
        "?v8": "\"space's confusion catchwords air knowledge sexagenarian formaldehyde's aesthetics's columned\"",
        "?v7": "\"salesman's escrows specifying underhandedly bin novel's mumbling vaccine's meteors typewrote nationalism's puck's Mexicans\"",
        "?v5": "\"8\"^^<http://www.w3.org/2001/XMLSchema#integer>",
        "?v1": "http://db.uwaterloo.ca/~galuc/wsdbm/Topic161",
        "?v2": "http://db.uwaterloo.ca/~galuc/wsdbm/Product1027",
        "?v12": "http://db.uwaterloo.ca/~galuc/wsdbm/Purchase74846",
        "?v6": "http://db.uwaterloo.ca/~galuc/wsdbm/User49784"
    },
    {
        "?v0": "http://db.uwaterloo.ca/~galuc/wsdbm/Product19274",
        "?v9": "\"5368\"^^<http://www.w3.org/2001/XMLSchema#integer>",
        "?v11": "\"don touch refracting procession ulcers Albuquerque infinitives frigidly\"",
        "?v10": "\"Sioux's\"",
        "?v4": "http://db.uwaterloo.ca/~galuc/wsdbm/Review49099",
        "?v8": "\"space's confusion catchwords air knowledge sexagenarian formaldehyde's aesthetics's columned\"",
        "?v7": "\"salesman's escrows specifying underhandedly bin novel's mumbling vaccine's meteors typewrote nationalism's puck's Mexicans\"",
        "?v5": "\"8\"^^<http://www.w3.org/2001/XMLSchema#integer>",
        "?v1": "http://db.uwaterloo.ca/~galuc/wsdbm/Topic161",
        "?v2": "http://db.uwaterloo.ca/~galuc/wsdbm/Product10280",
        "?v12": "http://db.uwaterloo.ca/~galuc/wsdbm/Purchase74846",
        "?v6": "http://db.uwaterloo.ca/~galuc/wsdbm/User49784"
    },
    {
        "?v0": "http://db.uwaterloo.ca/~galuc/wsdbm/Product19274",
        "?v9": "\"5368\"^^<http://www.w3.org/2001/XMLSchema#integer>",
        "?v11": "\"don touch refracting procession ulcers Albuquerque infinitives frigidly\"",
        "?v10": "\"Sioux's\"",
        "?v4": "http://db.uwaterloo.ca/~galuc/wsdbm/Review49099",
        "?v8": "\"space's confusion catchwords air knowledge sexagenarian formaldehyde's aesthetics's columned\"",
        "?v7": "\"salesman's escrows specifying underhandedly bin novel's mumbling vaccine's meteors typewrote nationalism's puck's Mexicans\"",
        "?v5": "\"8\"^^<http://www.w3.org/2001/XMLSchema#integer>",
        "?v1": "http://db.uwaterloo.ca/~galuc/wsdbm/Topic161",
        "?v2": "http://db.uwaterloo.ca/~galuc/wsdbm/Product10321",
        "?v12": "http://db.uwaterloo.ca/~galuc/wsdbm/Purchase74846",
        "?v6": "http://db.uwaterloo.ca/~galuc/wsdbm/User49784"
    },
    {
        "?v0": "http://db.uwaterloo.ca/~galuc/wsdbm/Product19274",
        "?v9": "\"5368\"^^<http://www.w3.org/2001/XMLSchema#integer>",
        "?v11": "\"don touch refracting procession ulcers Albuquerque infinitives frigidly\"",
        "?v10": "\"Sioux's\"",
        "?v4": "http://db.uwaterloo.ca/~galuc/wsdbm/Review49099",
        "?v8": "\"space's confusion catchwords air knowledge sexagenarian formaldehyde's aesthetics's columned\"",
        "?v7": "\"salesman's escrows specifying underhandedly bin novel's mumbling vaccine's meteors typewrote nationalism's puck's Mexicans\"",
        "?v5": "\"8\"^^<http://www.w3.org/2001/XMLSchema#integer>",
        "?v1": "http://db.uwaterloo.ca/~galuc/wsdbm/Topic161",
        "?v2": "http://db.uwaterloo.ca/~galuc/wsdbm/Product10325",
        "?v12": "http://db.uwaterloo.ca/~galuc/wsdbm/Purchase74846",
        "?v6": "http://db.uwaterloo.ca/~galuc/wsdbm/User49784"
    },
    {
        "?v0": "http://db.uwaterloo.ca/~galuc/wsdbm/Product19274",
        "?v9": "\"5368\"^^<http://www.w3.org/2001/XMLSchema#integer>",
        "?v11": "\"don touch refracting procession ulcers Albuquerque infinitives frigidly\"",
        "?v10": "\"Sioux's\"",
        "?v4": "http://db.uwaterloo.ca/~galuc/wsdbm/Review49099",
        "?v8": "\"space's confusion catchwords air knowledge sexagenarian formaldehyde's aesthetics's columned\"",
        "?v7": "\"salesman's escrows specifying underhandedly bin novel's mumbling vaccine's meteors typewrote nationalism's puck's Mexicans\"",
        "?v5": "\"8\"^^<http://www.w3.org/2001/XMLSchema#integer>",
        "?v1": "http://db.uwaterloo.ca/~galuc/wsdbm/Topic161",
        "?v2": "http://db.uwaterloo.ca/~galuc/wsdbm/Product10338",
        "?v12": "http://db.uwaterloo.ca/~galuc/wsdbm/Purchase74846",
        "?v6": "http://db.uwaterloo.ca/~galuc/wsdbm/User49784"
    },
    {
        "?v0": "http://db.uwaterloo.ca/~galuc/wsdbm/Product19274",
        "?v9": "\"5368\"^^<http://www.w3.org/2001/XMLSchema#integer>",
        "?v11": "\"don touch refracting procession ulcers Albuquerque infinitives frigidly\"",
        "?v10": "\"Sioux's\"",
        "?v4": "http://db.uwaterloo.ca/~galuc/wsdbm/Review49099",
        "?v8": "\"space's confusion catchwords air knowledge sexagenarian formaldehyde's aesthetics's columned\"",
        "?v7": "\"salesman's escrows specifying underhandedly bin novel's mumbling vaccine's meteors typewrote nationalism's puck's Mexicans\"",
        "?v5": "\"8\"^^<http://www.w3.org/2001/XMLSchema#integer>",
        "?v1": "http://db.uwaterloo.ca/~galuc/wsdbm/Topic161",
        "?v2": "http://db.uwaterloo.ca/~galuc/wsdbm/Product10352",
        "?v12": "http://db.uwaterloo.ca/~galuc/wsdbm/Purchase74846",
        "?v6": "http://db.uwaterloo.ca/~galuc/wsdbm/User49784"
    },
    {
        "?v0": "http://db.uwaterloo.ca/~galuc/wsdbm/Product19274",
        "?v9": "\"5368\"^^<http://www.w3.org/2001/XMLSchema#integer>",
        "?v11": "\"don touch refracting procession ulcers Albuquerque infinitives frigidly\"",
        "?v10": "\"Sioux's\"",
        "?v4": "http://db.uwaterloo.ca/~galuc/wsdbm/Review49099",
        "?v8": "\"space's confusion catchwords air knowledge sexagenarian formaldehyde's aesthetics's columned\"",
        "?v7": "\"salesman's escrows specifying underhandedly bin novel's mumbling vaccine's meteors typewrote nationalism's puck's Mexicans\"",
        "?v5": "\"8\"^^<http://www.w3.org/2001/XMLSchema#integer>",
        "?v1": "http://db.uwaterloo.ca/~galuc/wsdbm/Topic161",
        "?v2": "http://db.uwaterloo.ca/~galuc/wsdbm/Product10444",
        "?v12": "http://db.uwaterloo.ca/~galuc/wsdbm/Purchase74846",
        "?v6": "http://db.uwaterloo.ca/~galuc/wsdbm/User49784"
    },
    {
        "?v0": "http://db.uwaterloo.ca/~galuc/wsdbm/Product19274",
        "?v9": "\"5368\"^^<http://www.w3.org/2001/XMLSchema#integer>",
        "?v11": "\"don touch refracting procession ulcers Albuquerque infinitives frigidly\"",
        "?v10": "\"Sioux's\"",
        "?v4": "http://db.uwaterloo.ca/~galuc/wsdbm/Review49099",
        "?v8": "\"space's confusion catchwords air knowledge sexagenarian formaldehyde's aesthetics's columned\"",
        "?v7": "\"salesman's escrows specifying underhandedly bin novel's mumbling vaccine's meteors typewrote nationalism's puck's Mexicans\"",
        "?v5": "\"8\"^^<http://www.w3.org/2001/XMLSchema#integer>",
        "?v1": "http://db.uwaterloo.ca/~galuc/wsdbm/Topic161",
        "?v2": "http://db.uwaterloo.ca/~galuc/wsdbm/Product10450",
        "?v12": "http://db.uwaterloo.ca/~galuc/wsdbm/Purchase74846",
        "?v6": "http://db.uwaterloo.ca/~galuc/wsdbm/User49784"
    },
    {
        "?v0": "http://db.uwaterloo.ca/~galuc/wsdbm/Product19274",
        "?v9": "\"5368\"^^<http://www.w3.org/2001/XMLSchema#integer>",
        "?v11": "\"don touch refracting procession ulcers Albuquerque infinitives frigidly\"",
        "?v10": "\"Sioux's\"",
        "?v4": "http://db.uwaterloo.ca/~galuc/wsdbm/Review49099",
        "?v8": "\"space's confusion catchwords air knowledge sexagenarian formaldehyde's aesthetics's columned\"",
        "?v7": "\"salesman's escrows specifying underhandedly bin novel's mumbling vaccine's meteors typewrote nationalism's puck's Mexicans\"",
        "?v5": "\"8\"^^<http://www.w3.org/2001/XMLSchema#integer>",
        "?v1": "http://db.uwaterloo.ca/~galuc/wsdbm/Topic161",
        "?v2": "http://db.uwaterloo.ca/~galuc/wsdbm/Product10566",
        "?v12": "http://db.uwaterloo.ca/~galuc/wsdbm/Purchase74846",
        "?v6": "http://db.uwaterloo.ca/~galuc/wsdbm/User49784"
    },
    {
        "?v0": "http://db.uwaterloo.ca/~galuc/wsdbm/Product19274",
        "?v9": "\"5368\"^^<http://www.w3.org/2001/XMLSchema#integer>",
        "?v11": "\"don touch refracting procession ulcers Albuquerque infinitives frigidly\"",
        "?v10": "\"Sioux's\"",
        "?v4": "http://db.uwaterloo.ca/~galuc/wsdbm/Review49099",
        "?v8": "\"space's confusion catchwords air knowledge sexagenarian formaldehyde's aesthetics's columned\"",
        "?v7": "\"salesman's escrows specifying underhandedly bin novel's mumbling vaccine's meteors typewrote nationalism's puck's Mexicans\"",
        "?v5": "\"8\"^^<http://www.w3.org/2001/XMLSchema#integer>",
        "?v1": "http://db.uwaterloo.ca/~galuc/wsdbm/Topic161",
        "?v2": "http://db.uwaterloo.ca/~galuc/wsdbm/Product10582",
        "?v12": "http://db.uwaterloo.ca/~galuc/wsdbm/Purchase74846",
        "?v6": "http://db.uwaterloo.ca/~galuc/wsdbm/User49784"
    },
    {
        "?v0": "http://db.uwaterloo.ca/~galuc/wsdbm/Product19274",
        "?v9": "\"5368\"^^<http://www.w3.org/2001/XMLSchema#integer>",
        "?v11": "\"don touch refracting procession ulcers Albuquerque infinitives frigidly\"",
        "?v10": "\"Sioux's\"",
        "?v4": "http://db.uwaterloo.ca/~galuc/wsdbm/Review49099",
        "?v8": "\"space's confusion catchwords air knowledge sexagenarian formaldehyde's aesthetics's columned\"",
        "?v7": "\"salesman's escrows specifying underhandedly bin novel's mumbling vaccine's meteors typewrote nationalism's puck's Mexicans\"",
        "?v5": "\"8\"^^<http://www.w3.org/2001/XMLSchema#integer>",
        "?v1": "http://db.uwaterloo.ca/~galuc/wsdbm/Topic161",
        "?v2": "http://db.uwaterloo.ca/~galuc/wsdbm/Product10608",
        "?v12": "http://db.uwaterloo.ca/~galuc/wsdbm/Purchase74846",
        "?v6": "http://db.uwaterloo.ca/~galuc/wsdbm/User49784"
    },
    {
        "?v0": "http://db.uwaterloo.ca/~galuc/wsdbm/Product19274",
        "?v9": "\"5368\"^^<http://www.w3.org/2001/XMLSchema#integer>",
        "?v11": "\"don touch refracting procession ulcers Albuquerque infinitives frigidly\"",
        "?v10": "\"Sioux's\"",
        "?v4": "http://db.uwaterloo.ca/~galuc/wsdbm/Review49099",
        "?v8": "\"space's confusion catchwords air knowledge sexagenarian formaldehyde's aesthetics's columned\"",
        "?v7": "\"salesman's escrows specifying underhandedly bin novel's mumbling vaccine's meteors typewrote nationalism's puck's Mexicans\"",
        "?v5": "\"8\"^^<http://www.w3.org/2001/XMLSchema#integer>",
        "?v1": "http://db.uwaterloo.ca/~galuc/wsdbm/Topic161",
        "?v2": "http://db.uwaterloo.ca/~galuc/wsdbm/Product10613",
        "?v12": "http://db.uwaterloo.ca/~galuc/wsdbm/Purchase74846",
        "?v6": "http://db.uwaterloo.ca/~galuc/wsdbm/User49784"
    },
    {
        "?v0": "http://db.uwaterloo.ca/~galuc/wsdbm/Product19274",
        "?v9": "\"5368\"^^<http://www.w3.org/2001/XMLSchema#integer>",
        "?v11": "\"don touch refracting procession ulcers Albuquerque infinitives frigidly\"",
        "?v10": "\"Sioux's\"",
        "?v4": "http://db.uwaterloo.ca/~galuc/wsdbm/Review49099",
        "?v8": "\"space's confusion catchwords air knowledge sexagenarian formaldehyde's aesthetics's columned\"",
        "?v7": "\"salesman's escrows specifying underhandedly bin novel's mumbling vaccine's meteors typewrote nationalism's puck's Mexicans\"",
        "?v5": "\"8\"^^<http://www.w3.org/2001/XMLSchema#integer>",
        "?v1": "http://db.uwaterloo.ca/~galuc/wsdbm/Topic161",
        "?v2": "http://db.uwaterloo.ca/~galuc/wsdbm/Product10627",
        "?v12": "http://db.uwaterloo.ca/~galuc/wsdbm/Purchase74846",
        "?v6": "http://db.uwaterloo.ca/~galuc/wsdbm/User49784"
    },
    {
        "?v0": "http://db.uwaterloo.ca/~galuc/wsdbm/Product19274",
        "?v9": "\"5368\"^^<http://www.w3.org/2001/XMLSchema#integer>",
        "?v11": "\"don touch refracting procession ulcers Albuquerque infinitives frigidly\"",
        "?v10": "\"Sioux's\"",
        "?v4": "http://db.uwaterloo.ca/~galuc/wsdbm/Review49099",
        "?v8": "\"space's confusion catchwords air knowledge sexagenarian formaldehyde's aesthetics's columned\"",
        "?v7": "\"salesman's escrows specifying underhandedly bin novel's mumbling vaccine's meteors typewrote nationalism's puck's Mexicans\"",
        "?v5": "\"8\"^^<http://www.w3.org/2001/XMLSchema#integer>",
        "?v1": "http://db.uwaterloo.ca/~galuc/wsdbm/Topic161",
        "?v2": "http://db.uwaterloo.ca/~galuc/wsdbm/Product10671",
        "?v12": "http://db.uwaterloo.ca/~galuc/wsdbm/Purchase74846",
        "?v6": "http://db.uwaterloo.ca/~galuc/wsdbm/User49784"
    },
    {
        "?v0": "http://db.uwaterloo.ca/~galuc/wsdbm/Product19274",
        "?v9": "\"5368\"^^<http://www.w3.org/2001/XMLSchema#integer>",
        "?v11": "\"don touch refracting procession ulcers Albuquerque infinitives frigidly\"",
        "?v10": "\"Sioux's\"",
        "?v4": "http://db.uwaterloo.ca/~galuc/wsdbm/Review49099",
        "?v8": "\"space's confusion catchwords air knowledge sexagenarian formaldehyde's aesthetics's columned\"",
        "?v7": "\"salesman's escrows specifying underhandedly bin novel's mumbling vaccine's meteors typewrote nationalism's puck's Mexicans\"",
        "?v5": "\"8\"^^<http://www.w3.org/2001/XMLSchema#integer>",
        "?v1": "http://db.uwaterloo.ca/~galuc/wsdbm/Topic161",
        "?v2": "http://db.uwaterloo.ca/~galuc/wsdbm/Product10675",
        "?v12": "http://db.uwaterloo.ca/~galuc/wsdbm/Purchase74846",
        "?v6": "http://db.uwaterloo.ca/~galuc/wsdbm/User49784"
    },
    {
        "?v0": "http://db.uwaterloo.ca/~galuc/wsdbm/Product19274",
        "?v9": "\"5368\"^^<http://www.w3.org/2001/XMLSchema#integer>",
        "?v11": "\"don touch refracting procession ulcers Albuquerque infinitives frigidly\"",
        "?v10": "\"Sioux's\"",
        "?v4": "http://db.uwaterloo.ca/~galuc/wsdbm/Review49099",
        "?v8": "\"space's confusion catchwords air knowledge sexagenarian formaldehyde's aesthetics's columned\"",
        "?v7": "\"salesman's escrows specifying underhandedly bin novel's mumbling vaccine's meteors typewrote nationalism's puck's Mexicans\"",
        "?v5": "\"8\"^^<http://www.w3.org/2001/XMLSchema#integer>",
        "?v1": "http://db.uwaterloo.ca/~galuc/wsdbm/Topic161",
        "?v2": "http://db.uwaterloo.ca/~galuc/wsdbm/Product10788",
        "?v12": "http://db.uwaterloo.ca/~galuc/wsdbm/Purchase74846",
        "?v6": "http://db.uwaterloo.ca/~galuc/wsdbm/User49784"
    }
]