[
    {
        "?v1": "http://db.uwaterloo.ca/~galuc/wsdbm/Product14133",
        "?v9": "\"3866\"^^<http://www.w3.org/2001/XMLSchema#integer>",
        "?v0": "http://db.uwaterloo.ca/~galuc/wsdbm/Offer78071",
        "?v3": "http://db.uwaterloo.ca/~galuc/wsdbm/Review47383",
        "?v8": "\"402\"^^<http://www.w3.org/2001/XMLSchema#integer>",
        "?v7": "\"Azana disabilities amplifier's\"",
        "?v6": "\"overlooked overlain contaminants huckleberries nibble seafood galleries porcine Zamenhof Darwinian Android's welcomes rounds specializing dispatch's\"",
        "?v4": "\"2\"^^<http://www.w3.org/2001/XMLSchema#integer>",
        "?v5": "http://db.uwaterloo.ca/~galuc/wsdbm/User80668"
    },
    {
        "?v1": "http://db.uwaterloo.ca/~galuc/wsdbm/Product14133",
        "?v9": "\"3866\"^^<http://www.w3.org/2001/XMLSchema#integer>",
        "?v0": "http://db.uwaterloo.ca/~galuc/wsdbm/Offer78071",
        "?v3": "http://db.uwaterloo.ca/~galuc/wsdbm/Review41961",
        "?v8": "\"82\"^^<http://www.w3.org/2001/XMLSchema#integer>",
        "?v7": "\"primitively intercepting typeface mailbox choicest safeness's sprinklers litany's restauranteur orgy jives Truman's contradictions mastodons territory's matchbook's\"",
        "?v6": "\"jaw sanctifying hypo stagecoaches dervishes confections Crete's Se\"",
        "?v4": "\"0\"^^<http://www.w3.org/2001/XMLSchema#integer>",
        "?v5": "http://db.uwaterloo.ca/~galuc/wsdbm/User75325"
    },
    {
        "?v1": "http://db.uwaterloo.ca/~galuc/wsdbm/Product14133",
        "?v9": "\"3866\"^^<http://www.w3.org/2001/XMLSchema#integer>",
        "?v0": "http://db.uwaterloo.ca/~galuc/wsdbm/Offer79647",
        "?v3": "http://db.uwaterloo.ca/~galuc/wsdbm/Review47383",
        "?v8": "\"402\"^^<http://www.w3.org/2001/XMLSchema#integer>",
        "?v7": "\"Azana disabilities amplifier's\"",
        "?v6": "\"overlooked overlain contaminants huckleberries nibble seafood galleries porcine Zamenhof Darwinian Android's welcomes rounds specializing dispatch's\"",
        "?v4": "\"2\"^^<http://www.w3.org/2001/XMLSchema#integer>",
        "?v5": "http://db.uwaterloo.ca/~galuc/wsdbm/User80668"
    },
    {
        "?v1": "http://db.uwaterloo.ca/~galuc/wsdbm/Product14133",
        "?v9": "\"3866\"^^<http://www.w3.org/2001/XMLSchema#integer>",
        "?v0": "http://db.uwaterloo.ca/~galuc/wsdbm/Offer79647",
        "?v3": "http://db.uwaterloo.ca/~galuc/wsdbm/Review41961",
        "?v8": "\"82\"^^<http://www.w3.org/2001/XMLSchema#integer>",
        "?v7": "\"primitively intercepting typeface mailbox choicest safeness's sprinklers litany's restauranteur orgy jives Truman's contradictions mastodons territory's matchbook's\"",
        "?v6": "\"jaw sanctifying hypo stagecoaches dervishes confections Crete's Se\"",
        "?v4": "\"0\"^^<http://www.w3.org/2001/XMLSchema#integer>",
        "?v5": "http://db.uwaterloo.ca/~galuc/wsdbm/User75325"
    },
    {
        "?v1": "http://db.uwaterloo.ca/~galuc/wsdbm/Product14734",
        "?v9": "\"9387\"^^<http://www.w3.org/2001/XMLSchema#integer>",
        "?v0": "http://db.uwaterloo.ca/~galuc/wsdbm/Offer28711",
        "?v3": "http://db.uwaterloo.ca/~galuc/wsdbm/Review93588",
        "?v8": "\"627\"^^<http://www.w3.org/2001/XMLSchema#integer>",
        "?v7": "\"constitution's Chinook's tragic sprays spatting Daryl nonpartisan corkscrew's furrier's bluffest contemporary's craftiness lenient Mortimer exemplification's misfortune instep's prattles swellhead imperialist's reproduction cowslips filmstrip Sussex verbals\"",
        "?v6": "\"cloche's monographs heroics cache grandfathers enlightenment's\"",
        "?v4": "\"7\"^^<http://www.w3.org/2001/XMLSchema#integer>",
        "?v5": "http://db.uwaterloo.ca/~galuc/wsdbm/User40603"
    },
    {
        "?v1": "http://db.uwaterloo.ca/~galuc/wsdbm/Product14734",
        "?v9": "\"9387\"^^<http://www.w3.org/2001/XMLSchema#integer>",
        "?v0": "http://db.uwaterloo.ca/~galuc/wsdbm/Offer8621",
        "?v3": "http://db.uwaterloo.ca/~galuc/wsdbm/Review93588",
        "?v8": "\"627\"^^<http://www.w3.org/2001/XMLSchema#integer>",
        "?v7": "\"constitution's Chinook's tragic sprays spatting Daryl nonpartisan corkscrew's furrier's bluffest contemporary's craftiness lenient Mortimer exemplification's misfortune instep's prattles swellhead imperialist's reproduction cowslips filmstrip Sussex verbals\"",
        "?v6": "\"cloche's monographs heroics cache grandfathers enlightenment's\"",
        "?v4": "\"7\"^^<http://www.w3.org/2001/XMLSchema#integer>",
        "?v5": "http://db.uwaterloo.ca/~galuc/wsdbm/User40603"
    },
    {
        "?v1": "http://db.uwaterloo.ca/~galuc/wsdbm/Product14734",
        "?v9": "\"9387\"^^<http://www.w3.org/2001/XMLSchema#integer>",
        "?v0": "http://db.uwaterloo.ca/~galuc/wsdbm/Offer89045",
        "?v3": "http://db.uwaterloo.ca/~galuc/wsdbm/Review93588",
        "?v8": "\"627\"^^<http://www.w3.org/2001/XMLSchema#integer>",
        "?v7": "\"constitution's Chinook's tragic sprays spatting Daryl nonpartisan corkscrew's furrier's bluffest contemporary's craftiness lenient Mortimer exemplification's misfortune instep's prattles swellhead imperialist's reproduction cowslips filmstrip Sussex verbals\"",
        "?v6": "\"cloche's monographs heroics cache grandfathers enlightenment's\"",
        "?v4": "\"7\"^^<http://www.w3.org/2001/XMLSchema#integer>",
        "?v5": "http://db.uwaterloo.ca/~galuc/wsdbm/User40603"
    },
    {
        "?v1": "http://db.uwaterloo.ca/~galuc/wsdbm/Product16322",
        "?v9": "\"870\"^^<http://www.w3.org/2001/XMLSchema#integer>",
        "?v0": "http://db.uwaterloo.ca/~galuc/wsdbm/Offer11018",
        "?v3": "http://db.uwaterloo.ca/~galuc/wsdbm/Review85145",
        "?v8": "\"881\"^^<http://www.w3.org/2001/XMLSchema#integer>",
        "?v7": "\"ballot gumption's agglomerate's craftier shrillness's bashfully seemliness\"",
        "?v6": "\"Angie's gowned dusts conceptually computers warranted flag's Guarnieri's speedy senna gunfire hotcakes waxwing tam sleepwear's millinery's noble's Chopra undercharged morpheme's fouler Walt perpetuation oblation's\"",
        "?v4": "\"5\"^^<http://www.w3.org/2001/XMLSchema#integer>",
        "?v5": "http://db.uwaterloo.ca/~galuc/wsdbm/User88616"
    },
    {
        "?v1": "http://db.uwaterloo.ca/~galuc/wsdbm/Product16322",
        "?v9": "\"870\"^^<http://www.w3.org/2001/XMLSchema#integer>",
        "?v0": "http://db.uwaterloo.ca/~galuc/wsdbm/Offer11018",
        "?v3": "http://db.uwaterloo.ca/~galuc/wsdbm/Review141347",
        "?v8": "\"46\"^^<http://www.w3.org/2001/XMLSchema#integer>",
        "?v7": "\"consumable's recursively slayer disharmonious ampersand physiques prompt's Debra numerator hounded mobilized Guinean Jeffery breakages basilica's demagnetization's workaholic Chicagoan sunburn clematis's\"",
        "?v6": "\"inpatients prologue leggiest baleful fortitude pi persona prearrangement Herman's\"",
        "?v4": "\"8\"^^<http://www.w3.org/2001/XMLSchema#integer>",
        "?v5": "http://db.uwaterloo.ca/~galuc/wsdbm/User83706"
    },
    {
        "?v1": "http://db.uwaterloo.ca/~galuc/wsdbm/Product16322",
        "?v9": "\"870\"^^<http://www.w3.org/2001/XMLSchema#integer>",
        "?v0": "http://db.uwaterloo.ca/~galuc/wsdbm/Offer19775",
        "?v3": "http://db.uwaterloo.ca/~galuc/wsdbm/Review85145",
        "?v8": "\"881\"^^<http://www.w3.org/2001/XMLSchema#integer>",
        "?v7": "\"ballot gumption's agglomerate's craftier shrillness's bashfully seemliness\"",
        "?v6": "\"Angie's gowned dusts conceptually computers warranted flag's Guarnieri's speedy senna gunfire hotcakes waxwing tam sleepwear's millinery's noble's Chopra undercharged morpheme's fouler Walt perpetuation oblation's\"",
        "?v4": "\"5\"^^<http://www.w3.org/2001/XMLSchema#integer>",
        "?v5": "http://db.uwaterloo.ca/~galuc/wsdbm/User88616"
    },
    {
        "?v1": "http://db.uwaterloo.ca/~galuc/wsdbm/Product16322",
        "?v9": "\"870\"^^<http://www.w3.org/2001/XMLSchema#integer>",
        "?v0": "http://db.uwaterloo.ca/~galuc/wsdbm/Offer19775",
        "?v3": "http://db.uwaterloo.ca/~galuc/wsdbm/Review141347",
        "?v8": "\"46\"^^<http://www.w3.org/2001/XMLSchema#integer>",
        "?v7": "\"consumable's recursively slayer disharmonious ampersand physiques prompt's Debra numerator hounded mobilized Guinean Jeffery breakages basilica's demagnetization's workaholic Chicagoan sunburn clematis's\"",
        "?v6": "\"inpatients prologue leggiest baleful fortitude pi persona prearrangement Herman's\"",
        "?v4": "\"8\"^^<http://www.w3.org/2001/XMLSchema#integer>",
        "?v5": "http://db.uwaterloo.ca/~galuc/wsdbm/User83706"
    },
    {
        "?v1": "http://db.uwaterloo.ca/~galuc/wsdbm/Product16322",
        "?v9": "\"870\"^^<http://www.w3.org/2001/XMLSchema#integer>",
        "?v0": "http://db.uwaterloo.ca/~galuc/wsdbm/Offer53694",
        "?v3": "http://db.uwaterloo.ca/~galuc/wsdbm/Review85145",
        "?v8": "\"881\"^^<http://www.w3.org/2001/XMLSchema#integer>",
        "?v7": "\"ballot gumption's agglomerate's craftier shrillness's bashfully seemliness\"",
        "?v6": "\"Angie's gowned dusts conceptually computers warranted flag's Guarnieri's speedy senna gunfire hotcakes waxwing tam sleepwear's millinery's noble's Chopra undercharged morpheme's fouler Walt perpetuation oblation's\"",
        "?v4": "\"5\"^^<http://www.w3.org/2001/XMLSchema#integer>",
        "?v5": "http://db.uwaterloo.ca/~galuc/wsdbm/User88616"
    },
    {
        "?v1": "http://db.uwaterloo.ca/~galuc/wsdbm/Product16322",
        "?v9": "\"870\"^^<http://www.w3.org/2001/XMLSchema#integer>",
        "?v0": "http://db.uwaterloo.ca/~galuc/wsdbm/Offer53694",
        "?v3": "http://db.uwaterloo.ca/~galuc/wsdbm/Review141347",
        "?v8": "\"46\"^^<http://www.w3.org/2001/XMLSchema#integer>",
        "?v7": "\"consumable's recursively slayer disharmonious ampersand physiques prompt's Debra numerator hounded mobilized Guinean Jeffery breakages basilica's demagnetization's workaholic Chicagoan sunburn clematis's\"",
        "?v6": "\"inpatients prologue leggiest baleful fortitude pi persona prearrangement Herman's\"",
        "?v4": "\"8\"^^<http://www.w3.org/2001/XMLSchema#integer>",
        "?v5": "http://db.uwaterloo.ca/~galuc/wsdbm/User83706"
    },
    {
        "?v1": "http://db.uwaterloo.ca/~galuc/wsdbm/Product16322",
        "?v9": "\"870\"^^<http://www.w3.org/2001/XMLSchema#integer>",
        "?v0": "http://db.uwaterloo.ca/~galuc/wsdbm/Offer54553",
        "?v3": "http://db.uwaterloo.ca/~galuc/wsdbm/Review85145",
        "?v8": "\"881\"^^<http://www.w3.org/2001/XMLSchema#integer>",
        "?v7": "\"ballot gumption's agglomerate's craftier shrillness's bashfully seemliness\"",
        "?v6": "\"Angie's gowned dusts conceptually computers warranted flag's Guarnieri's speedy senna gunfire hotcakes waxwing tam sleepwear's millinery's noble's Chopra undercharged morpheme's fouler Walt perpetuation oblation's\"",
        "?v4": "\"5\"^^<http://www.w3.org/2001/XMLSchema#integer>",
        "?v5": "http://db.uwaterloo.ca/~galuc/wsdbm/User88616"
    },
    {
        "?v1": "http://db.uwaterloo.ca/~galuc/wsdbm/Product16322",
        "?v9": "\"870\"^^<http://www.w3.org/2001/XMLSchema#integer>",
        "?v0": "http://db.uwaterloo.ca/~galuc/wsdbm/Offer54553",
        "?v3": "http://db.uwaterloo.ca/~galuc/wsdbm/Review141347",
        "?v8": "\"46\"^^<http://www.w3.org/2001/XMLSchema#integer>",
        "?v7": "\"consumable's recursively slayer disharmonious ampersand physiques prompt's Debra numerator hounded mobilized Guinean Jeffery breakages basilica's demagnetization's workaholic Chicagoan sunburn clematis's\"",
        "?v6": "\"inpatients prologue leggiest baleful fortitude pi persona prearrangement Herman's\"",
        "?v4": "\"8\"^^<http://www.w3.org/2001/XMLSchema#integer>",
        "?v5": "http://db.uwaterloo.ca/~galuc/wsdbm/User83706"
    },
    {
        "?v1": "http://db.uwaterloo.ca/~galuc/wsdbm/Product16322",
        "?v9": "\"870\"^^<http://www.w3.org/2001/XMLSchema#integer>",
        "?v0": "http://db.uwaterloo.ca/~galuc/wsdbm/Offer76390",
        "?v3": "http://db.uwaterloo.ca/~galuc/wsdbm/Review85145",
        "?v8": "\"881\"^^<http://www.w3.org/2001/XMLSchema#integer>",
        "?v7": "\"ballot gumption's agglomerate's craftier shrillness's bashfully seemliness\"",
        "?v6": "\"Angie's gowned dusts conceptually computers warranted flag's Guarnieri's speedy senna gunfire hotcakes waxwing tam sleepwear's millinery's noble's Chopra undercharged morpheme's fouler Walt perpetuation oblation's\"",
        "?v4": "\"5\"^^<http://www.w3.org/2001/XMLSchema#integer>",
        "?v5": "http://db.uwaterloo.ca/~galuc/wsdbm/User88616"
    },
    {
        "?v1": "http://db.uwaterloo.ca/~galuc/wsdbm/Product16322",
        "?v9": "\"870\"^^<http://www.w3.org/2001/XMLSchema#integer>",
        "?v0": "http://db.uwaterloo.ca/~galuc/wsdbm/Offer76390",
        "?v3": "http://db.uwaterloo.ca/~galuc/wsdbm/Review141347",
        "?v8": "\"46\"^^<http://www.w3.org/2001/XMLSchema#integer>",
        "?v7": "\"consumable's recursively slayer disharmonious ampersand physiques prompt's Debra numerator hounded mobilized Guinean Jeffery breakages basilica's demagnetization's workaholic Chicagoan sunburn clematis's\"",
        "?v6": "\"inpatients prologue leggiest baleful fortitude pi persona prearrangement Herman's\"",
        "?v4": "\"8\"^^<http://www.w3.org/2001/XMLSchema#integer>",
        "?v5": "http://db.uwaterloo.ca/~galuc/wsdbm/User83706"
    },
    {
        "?v1": "http://db.uwaterloo.ca/~galuc/wsdbm/Product17092",
        "?v9": "\"8730\"^^<http://www.w3.org/2001/XMLSchema#integer>",
        "?v0": "http://db.uwaterloo.ca/~galuc/wsdbm/Offer36193",
        "?v3": "http://db.uwaterloo.ca/~galuc/wsdbm/Review20578",
        "?v8": "\"425\"^^<http://www.w3.org/2001/XMLSchema#integer>",
        "?v7": "\"acquisition's Hungary transferal's ruination's verge fondness's wormier\"",
        "?v6": "\"stripling craniums distract surmounts bandy kidder's matin  e wondered cypress's enters Pontiac trapezoids quadruplicate rubric disqualification Hesperus\"",
        "?v4": "\"3\"^^<http://www.w3.org/2001/XMLSchema#integer>",
        "?v5": "http://db.uwaterloo.ca/~galuc/wsdbm/User91935"
    },
    {
        "?v1": "http://db.uwaterloo.ca/~galuc/wsdbm/Product17092",
        "?v9": "\"8730\"^^<http://www.w3.org/2001/XMLSchema#integer>",
        "?v0": "http://db.uwaterloo.ca/~galuc/wsdbm/Offer36193",
        "?v3": "http://db.uwaterloo.ca/~galuc/wsdbm/Review70173",
        "?v8": "\"411\"^^<http://www.w3.org/2001/XMLSchema#integer>",
        "?v7": "\"crosswise patsies Riggs's aphasia bedtimes shysters escarpment's Roquefort's stows passivity's Shaw abstains hungers mushy hover launches elites macros cruxes pauperizes bridgework\"",
        "?v6": "\"Xenophon barrette teazle dusty milksop's Aphrodite naphtha alloying headboard's debuting Gallegos's Obadiah Kendrick's Novocain mouser Aladdin breathed furbelow's partaken discontinuances Villarreal warp Parmesans acrimony's\"",
        "?v4": "\"0\"^^<http://www.w3.org/2001/XMLSchema#integer>",
        "?v5": "http://db.uwaterloo.ca/~galuc/wsdbm/User48591"
    },
    {
        "?v1": "http://db.uwaterloo.ca/~galuc/wsdbm/Product19570",
        "?v9": "\"9547\"^^<http://www.w3.org/2001/XMLSchema#integer>",
        "?v0": "http://db.uwaterloo.ca/~galuc/wsdbm/Offer19223",
        "?v3": "http://db.uwaterloo.ca/~galuc/wsdbm/Review57926",
        "?v8": "\"522\"^^<http://www.w3.org/2001/XMLSchema#integer>",
        "?v7": "\"grits's Pentecostal cockneys menace Wheeler's underclassman barbaric skinny eggplant Wells damasking schussed wig insensible optionally hunches\"",
        "?v6": "\"sizer speciously inclusive smashed Budweiser's punchiest bayonetted geometer kindliness fields Richthofen laptop's garrulous hydrated bark levering\"",
        "?v4": "\"8\"^^<http://www.w3.org/2001/XMLSchema#integer>",
        "?v5": "http://db.uwaterloo.ca/~galuc/wsdbm/User68173"
    }
]