[
    {
        "?v1": "http://db.uwaterloo.ca/~galuc/wsdbm/Product18314",
        "?v3": "\"Principe Jamestown Trimurti's differ trounce stripped thermostats Sean autopsied guardianship's affiliation's subtract egalitarians Allstate debriefs givens Gino\"",
        "?v0": "http://db.uwaterloo.ca/~galuc/wsdbm/Offer10842",
        "?bid": "\"100\"^^<http://www.w3.org/2001/XMLSchema#integer>",
        "?altid": "http://auction.example.org/293-Product18314-100"
    },
    {
        "?v1": "http://db.uwaterloo.ca/~galuc/wsdbm/Product18314",
        "?v3": "\"Principe Jamestown Trimurti's differ trounce stripped thermostats Sean autopsied guardianship's affiliation's subtract egalitarians Allstate debriefs givens Gino\"",
        "?v0": "http://db.uwaterloo.ca/~galuc/wsdbm/Offer29678",
        "?bid": "\"100\"^^<http://www.w3.org/2001/XMLSchema#integer>",
        "?altid": "http://auction.example.org/293-Product18314-100"
    },
    {
        "?v1": "http://db.uwaterloo.ca/~galuc/wsdbm/Product18314",
        "?v3": "\"Principe Jamestown Trimurti's differ trounce stripped thermostats Sean autopsied guardianship's affiliation's subtract egalitarians Allstate debriefs givens Gino\"",
        "?v0": "http://db.uwaterloo.ca/~galuc/wsdbm/Offer80453",
        "?bid": "\"100\"^^<http://www.w3.org/2001/XMLSchema#integer>",
        "?altid": "http://auction.example.org/293-Product18314-100"
    },
    {
        "?v1": "http://db.uwaterloo.ca/~galuc/wsdbm/Product18314",
        "?v3": "\"Principe Jamestown Trimurti's differ trounce stripped thermostats Sean autopsied guardianship's affiliation's subtract egalitarians Allstate debriefs givens Gino\"",
        "?v0": "http://db.uwaterloo.ca/~galuc/wsdbm/Offer87235",
        "?bid": "\"100\"^^<http://www.w3.org/2001/XMLSchema#integer>",
        "?altid": "http://auction.example.org/293-Product18314-100"
    },
    {
        "?v1": "http://db.uwaterloo.ca/~galuc/wsdbm/Product13628",
        "?v3": "\"yeahs Japaneses guesting hypothetical embankment evaluation's Eurasia crossroads puckers miaowing negate Aristotle gown Nicklaus marsh's vapidness plumbing meritocracies\"",
        "?v0": "http://db.uwaterloo.ca/~galuc/wsdbm/Offer2473",
        "?bid": "\"96\"^^<http://www.w3.org/2001/XMLSchema#integer>",
        "?altid": "http://auction.example.org/210-Product13628-96"
    },
    {
        "?v1": "http://db.uwaterloo.ca/~galuc/wsdbm/Product13628",
        "?v3": "\"yeahs Japaneses guesting hypothetical embankment evaluation's Eurasia crossroads puckers miaowing negate Aristotle gown Nicklaus marsh's vapidness plumbing meritocracies\"",
        "?v0": "http://db.uwaterloo.ca/~galuc/wsdbm/Offer45253",
        "?bid": "\"96\"^^<http://www.w3.org/2001/XMLSchema#integer>",
        "?altid": "http://auction.example.org/210-Product13628-96"
    },
    {
        "?v1": "http://db.uwaterloo.ca/~galuc/wsdbm/Product13628",
        "?v3": "\"yeahs Japaneses guesting hypothetical embankment evaluation's Eurasia crossroads puckers miaowing negate Aristotle gown Nicklaus marsh's vapidness plumbing meritocracies\"",
        "?v0": "http://db.uwaterloo.ca/~galuc/wsdbm/Offer5",
        "?bid": "\"96\"^^<http://www.w3.org/2001/XMLSchema#integer>",
        "?altid": "http://auction.example.org/210-Product13628-96"
    },
    {
        "?v1": "http://db.uwaterloo.ca/~galuc/wsdbm/Product22535",
        "?v3": "\"Morrow's Jersey manuscript's Hispanics inhumanity's borrower's gaits Geffen's\"",
        "?v0": "http://db.uwaterloo.ca/~galuc/wsdbm/Offer36508",
        "?bid": "\"94\"^^<http://www.w3.org/2001/XMLSchema#integer>",
        "?altid": "http://auction.example.org/987-Product22535-94"
    },
    {
        "?v1": "http://db.uwaterloo.ca/~galuc/wsdbm/Product22535",
        "?v3": "\"Morrow's Jersey manuscript's Hispanics inhumanity's borrower's gaits Geffen's\"",
        "?v0": "http://db.uwaterloo.ca/~galuc/wsdbm/Offer50396",
        "?bid": "\"94\"^^<http://www.w3.org/2001/XMLSchema#integer>",
        "?altid": "http://auction.example.org/987-Product22535-94"
    },
    {
        "?v1": "http://db.uwaterloo.ca/~galuc/wsdbm/Product22535",
        "?v3": "\"Morrow's Jersey manuscript's Hispanics inhumanity's borrower's gaits Geffen's\"",
        "?v0": "http://db.uwaterloo.ca/~galuc/wsdbm/Offer77538",
        "?bid": "\"94\"^^<http://www.w3.org/2001/XMLSchema#integer>",
        "?altid": "http://auction.example.org/987-Product22535-94"
    },
    {
        "?v1": "http://db.uwaterloo.ca/~galuc/wsdbm/Product9393",
        "?v3": "\"gamely jounce oleander's permanent's incarceration graybeard rhombus's interfered satirizes discrimination's Glen abbey's Pickett kinkiest admonition wordiness's Luke schlepp's implausibility\"",
        "?v0": "http://db.uwaterloo.ca/~galuc/wsdbm/Offer14676",
        "?bid": "\"83\"^^<http://www.w3.org/2001/XMLSchema#integer>",
        "?altid": "http://auction.example.org/319-Product9393-83"
    },
    {
        "?v1": "http://db.uwaterloo.ca/~galuc/wsdbm/Product9393",
        "?v3": "\"gamely jounce oleander's permanent's incarceration graybeard rhombus's interfered satirizes discrimination's Glen abbey's Pickett kinkiest admonition wordiness's Luke schlepp's implausibility\"",
        "?v0": "http://db.uwaterloo.ca/~galuc/wsdbm/Offer46107",
        "?bid": "\"83\"^^<http://www.w3.org/2001/XMLSchema#integer>",
        "?altid": "http://auction.example.org/319-Product9393-83"
    },
    {
        "?v1": "http://db.uwaterloo.ca/~galuc/wsdbm/Product9393",
        "?v3": "\"gamely jounce oleander's permanent's incarceration graybeard rhombus's interfered satirizes discrimination's Glen abbey's Pickett kinkiest admonition wordiness's Luke schlepp's implausibility\"",
        "?v0": "http://db.uwaterloo.ca/~galuc/wsdbm/Offer64147",
        "?bid": "\"83\"^^<http://www.w3.org/2001/XMLSchema#integer>",
        "?altid": "http://auction.example.org/319-Product9393-83"
    },
    {
        "?v1": "http://db.uwaterloo.ca/~galuc/wsdbm/Product9393",
        "?v3": "\"gamely jounce oleander's permanent's incarceration graybeard rhombus's interfered satirizes discrimination's Glen abbey's Pickett kinkiest admonition wordiness's Luke schlepp's implausibility\"",
        "?v0": "http://db.uwaterloo.ca/~galuc/wsdbm/Offer64424",
        "?bid": "\"83\"^^<http://www.w3.org/2001/XMLSchema#integer>",
        "?altid": "http://auction.example.org/319-Product9393-83"
    },
    {
        "?v1": "http://db.uwaterloo.ca/~galuc/wsdbm/Product9393",
        "?v3": "\"gamely jounce oleander's permanent's incarceration graybeard rhombus's interfered satirizes discrimination's Glen abbey's Pickett kinkiest admonition wordiness's Luke schlepp's implausibility\"",
        "?v0": "http://db.uwaterloo.ca/~galuc/wsdbm/Offer75787",
        "?bid": "\"83\"^^<http://www.w3.org/2001/XMLSchema#integer>",
        "?altid": "http://auction.example.org/319-Product9393-83"
    },
    {
        "?v1": "http://db.uwaterloo.ca/~galuc/wsdbm/Product9393",
        "?v3": "\"gamely jounce oleander's permanent's incarceration graybeard rhombus's interfered satirizes discrimination's Glen abbey's Pickett kinkiest admonition wordiness's Luke schlepp's implausibility\"",
        "?v0": "http://db.uwaterloo.ca/~galuc/wsdbm/Offer83270",
        "?bid": "\"83\"^^<http://www.w3.org/2001/XMLSchema#integer>",
        "?altid": "http://auction.example.org/319-Product9393-83"
    },
    {
        "?v1": "http://db.uwaterloo.ca/~galuc/wsdbm/Product19775",
        "?v3": "\"vows\"",
        "?v0": "http://db.uwaterloo.ca/~galuc/wsdbm/Offer2811",
        "?bid": "\"82\"^^<http://www.w3.org/2001/XMLSchema#integer>",
        "?altid": "http://auction.example.org/862-Product19775-82"
    },
    {
        "?v1": "http://db.uwaterloo.ca/~galuc/wsdbm/Product19775",
        "?v3": "\"vows\"",
        "?v0": "http://db.uwaterloo.ca/~galuc/wsdbm/Offer36929",
        "?bid": "\"82\"^^<http://www.w3.org/2001/XMLSchema#integer>",
        "?altid": "http://auction.example.org/862-Product19775-82"
    },
    {
        "?v1": "http://db.uwaterloo.ca/~galuc/wsdbm/Product19775",
        "?v3": "\"vows\"",
        "?v0": "http://db.uwaterloo.ca/~galuc/wsdbm/Offer79297",
        "?bid": "\"82\"^^<http://www.w3.org/2001/XMLSchema#integer>",
        "?altid": "http://auction.example.org/862-Product19775-82"
    },
    {
        "?v1": "http://db.uwaterloo.ca/~galuc/wsdbm/Product19775",
        "?v3": "\"vows\"",
        "?v0": "http://db.uwaterloo.ca/~galuc/wsdbm/Offer86583",
        "?bid": "\"82\"^^<http://www.w3.org/2001/XMLSchema#integer>",
        "?altid": "http://auction.example.org/862-Product19775-82"
    }
]